schemarrow/__init__.py
schemarrow/mappers/__init__.py
schemarrow/mappers/datetime_mapper.py
schemarrow/mappers/db_types.py
schemarrow/mappers/dtype_mapper.py
schemarrow/mappers/numeric_mapper.py
schemarrow/schema_arrow.py
schemarrow-0.1.1a0.dist-info/LICENSE
schemarrow-0.1.1a0.dist-info/METADATA
schemarrow-0.1.1a0.dist-info/WHEEL
schemarrow-0.1.1a0.dist-info/RECORD
