Metadata-Version: 2.1
Name: schemarrow
Version: 0.1.1a0
Summary: A library for switching pandas backend to pyarrow
Home-page: https://github.com/DanielAvdar/SchemArrow
License: MIT
Keywords: pandas,pyarrow,arrow,schemarrow,pandas-pyarrow,pandas-arrow,pandas-backend,data-processing,data-conversion,backend-switch,high-performance,datasets,big-data,data-serialization,data-analysis,data-science,machine-learning,AI,python-library,data-backend,performance-optimization,memory-efficient,python
Author: DanielAvdar
Author-email: 66269169+DanielAvdar@users.noreply.github.com
Requires-Python: >=3.9,<3.13
Classifier: License :: OSI Approved :: MIT License
Classifier: Programming Language :: Python :: 3
Classifier: Programming Language :: Python :: 3.9
Classifier: Programming Language :: Python :: 3.10
Classifier: Programming Language :: Python :: 3.11
Classifier: Programming Language :: Python :: 3.12
Provides-Extra: db-dtypes
Requires-Dist: db-dtypes[db-dtypes] (>=1) ; extra == "db-dtypes"
Requires-Dist: pandas (>=2)
Requires-Dist: pyarrow (>=7.0.0,<=15.0.0)
Project-URL: Documentation, https://github.com/DanielAvdar/SchemArrow
Project-URL: Repository, https://github.com/DanielAvdar/SchemArrow
